[
  {
    "texture": "human-blank",
    "src": "./assets/atlas/human-blank.png",
    "atlas": "./assets/atlas/80x80.json",
    "previewRect": [0, 160, 80, 80]
  },
  {
    "texture": "shadow",
    "src": "./assets/atlas/shadow.png",
    "atlas": "./assets/atlas/80x80.json",
    "previewRect": [0, 160, 80, 80]
  },
  {
    "texture": "human",
    "src": "./assets/atlas/human.png",
    "atlas": "./assets/atlas/80x80.json",
    "previewRect": [0, 160, 80, 80]
  },
  {
    "texture": "human-male-chest-bare",
    "src": "./assets/atlas/male/chest/chest-bare.png",
    "atlas": "./assets/atlas/80x80.json",
    "previewRect": [0, 160, 80, 80]
  },
  {
    "texture": "human-face-1",
    "src": "./assets/atlas/face/face-1.png",
    "atlas": "./assets/atlas/80x80.json",
    "previewRect": [0, 160, 80, 80]
  },
  {
    "texture": "human-face-2",
    "src": "./assets/atlas/face/face-2.png",
    "atlas": "./assets/atlas/80x80.json",
    "previewRect": [0, 160, 80, 80]
  },
  {
    "texture": "human-face-3",
    "src": "./assets/atlas/face/face-3.png",
    "atlas": "./assets/atlas/80x80.json",
    "previewRect": [0, 160, 80, 80]
  },
  {
    "texture": "human-whiskers-0",
    "src": "./assets/atlas/human-blank.png",
    "atlas": "./assets/atlas/80x80.json",
    "previewRect": [0, 160, 80, 80]
  },
  {
    "texture": "human-whiskers-1",
    "src": "./assets/atlas/whiskers/whiskers-1.png",
    "atlas": "./assets/atlas/80x80.json",
    "previewRect": [0, 160, 80, 80]
  },
  {
    "texture": "human-whiskers-2",
    "src": "./assets/atlas/whiskers/whiskers-2.png",
    "atlas": "./assets/atlas/80x80.json",
    "previewRect": [0, 160, 80, 80]
  },
  {
    "texture": "human-whiskers-3",
    "src": "./assets/atlas/whiskers/whiskers-3.png",
    "atlas": "./assets/atlas/80x80.json",
    "previewRect": [0, 160, 80, 80]
  },
  {
    "texture": "human-hair-0",
    "src": "./assets/atlas/human-blank.png",
    "atlas": "./assets/atlas/80x80.json",
    "previewRect": [0, 160, 80, 80]
  },
  {
    "texture": "human-hair-1",
    "src": "./assets/atlas/hair/hair-1.png",
    "atlas": "./assets/atlas/80x80.json",
    "previewRect": [0, 160, 80, 80]
  },
  {
    "texture": "human-hair-2",
    "src": "./assets/atlas/hair/hair-2.png",
    "atlas": "./assets/atlas/80x80.json",
    "previewRect": [0, 160, 80, 80]
  },
  {
    "texture": "human-hair-3",
    "src": "./assets/atlas/hair/hair-3.png",
    "atlas": "./assets/atlas/80x80.json",
    "previewRect": [0, 160, 80, 80]
  },
  {
    "texture": "human-hair-4",
    "src": "./assets/atlas/hair/hair-4.png",
    "atlas": "./assets/atlas/80x80.json",
    "previewRect": [0, 160, 80, 80]
  },
  {
    "texture": "human-hair-5",
    "src": "./assets/atlas/hair/hair-5.png",
    "atlas": "./assets/atlas/80x80.json",
    "previewRect": [0, 160, 80, 80]
  },
  {
    "texture": "human-female-chest-bare",
    "src": "./assets/atlas/female/chest/chest-bare.png",
    "atlas": "./assets/atlas/80x80.json",
    "previewRect": [0, 160, 80, 80]
  },
  {
    "texture": "dog",
    "src": "./assets/atlas/mob/dog.png",
    "atlas": "./assets/atlas/50x50.json",
    "previewRect": [0, 100, 50, 50]
  },
  {
    "texture": "cat",
    "src": "./assets/atlas/mob/cat.png",
    "atlas": "./assets/atlas/50x50.json",
    "previewRect": [0, 100, 50, 50]
  },
  {
    "texture": "wyrm",
    "src": "./assets/atlas/mob/wyrm.png",
    "atlas": "./assets/atlas/50x50.json",
    "previewRect": [0, 100, 50, 50]
  },
  {
    "texture": "slime",
    "src": "./assets/atlas/mob/slime.png",
    "atlas": "./assets/atlas/80x80.json",
    "previewRect": [0, 160, 80, 80]
  },
  {
    "texture": "bee",
    "src": "./assets/atlas/mob/bee.png",
    "atlas": "./assets/atlas/80x80.json",
    "previewRect": [0, 160, 80, 80]
  },
  {
    "texture": "raccoon",
    "src": "./assets/atlas/mob/raccoon.png",
    "atlas": "./assets/atlas/80x80.json",
    "previewRect": [0, 160, 80, 80]
  },
  {
    "texture": "bat",
    "src": "./assets/atlas/mob/bat.png",
    "atlas": "./assets/atlas/80x80.json",
    "previewRect": [0, 160, 80, 80]
  },
  {
    "texture": "spider",
    "src": "./assets/atlas/mob/spider.png",
    "atlas": "./assets/atlas/80x80.json",
    "previewRect": [0, 160, 80, 80]
  },
  {
    "texture": "fish",
    "src": "./assets/atlas/mob/fish.png",
    "atlas": "./assets/atlas/80x80.json",
    "previewRect": [0, 160, 80, 80]
  },
  {
    "texture": "crab",
    "src": "./assets/atlas/mob/crab.png",
    "atlas": "./assets/atlas/80x80.json",
    "previewRect": [0, 160, 80, 80]
  },
  {
    "texture": "orchid",
    "src": "./assets/atlas/mob/orchid.png",
    "atlas": "./assets/atlas/80x80.json",
    "previewRect": [0, 160, 80, 80]
  },
  {
    "texture": "earth-elemental",
    "src": "./assets/atlas/mob/earth-elemental.png",
    "atlas": "./assets/atlas/80x80.json",
    "previewRect": [0, 160, 80, 80]
  },
  {
    "texture": "wolf",
    "src": "./assets/atlas/mob/wolf.png",
    "atlas": "./assets/atlas/80x80.json",
    "previewRect": [0, 160, 80, 80]
  },
  {
    "texture": "bear",
    "src": "./assets/atlas/mob/bear.png",
    "atlas": "./assets/atlas/80x80.json",
    "previewRect": [0, 160, 80, 80]
  },
  {
    "texture": "wraith",
    "src": "./assets/atlas/mob/wraith.png",
    "atlas": "./assets/atlas/80x80.json",
    "previewRect": [0, 160, 80, 80]
  },
  {
    "texture": "zombie",
    "src": "./assets/atlas/mob/zombie.png",
    "atlas": "./assets/atlas/80x80.json",
    "previewRect": [0, 160, 80, 80]
  },
  {
    "texture": "abomination",
    "src": "./assets/atlas/mob/abomination.png",
    "atlas": "./assets/atlas/150x150.json",
    "previewRect": [0, 300, 150, 150]
  },
  {
    "texture": "merman",
    "src": "./assets/atlas/mob/merman.png",
    "atlas": "./assets/atlas/80x80.json",
    "previewRect": [0, 160, 80, 80]
  },
  {
    "texture": "human-female-armor-plate-light",
    "src": "./assets/atlas/female/armor/armor-plate-light.png",
    "atlas": "./assets/atlas/80x80.json",
    "previewRect": [0, 160, 80, 80]
  },
  {
    "texture": "human-male-armor-plate-light",
    "src": "./assets/atlas/male/armor/armor-plate-light.png",
    "atlas": "./assets/atlas/80x80.json",
    "previewRect": [0, 160, 80, 80]
  },
  {
    "texture": "human-female-armor-plate",
    "src": "./assets/atlas/female/armor/armor-plate.png",
    "atlas": "./assets/atlas/80x80.json",
    "previewRect": [0, 160, 80, 80]
  },
  {
    "texture": "human-male-armor-plate",
    "src": "./assets/atlas/male/armor/armor-plate.png",
    "atlas": "./assets/atlas/80x80.json",
    "previewRect": [0, 160, 80, 80]
  },
  {
    "texture": "human-female-armor-robe",
    "src": "./assets/atlas/female/armor/armor-robe.png",
    "atlas": "./assets/atlas/80x80.json",
    "previewRect": [0, 160, 80, 80]
  },
  {
    "texture": "human-female-armor-coat-leather",
    "src": "./assets/atlas/female/armor/armor-coat-leather.png",
    "atlas": "./assets/atlas/80x80.json",
    "previewRect": [0, 160, 80, 80]
  },
  {
    "texture": "human-female-armor-coat",
    "src": "./assets/atlas/female/armor/armor-coat.png",
    "atlas": "./assets/atlas/80x80.json",
    "previewRect": [0, 160, 80, 80]
  },
  {
    "texture": "human-male-armor-robe",
    "src": "./assets/atlas/male/armor/armor-robe.png",
    "atlas": "./assets/atlas/80x80.json",
    "previewRect": [0, 160, 80, 80]
  },
  {
    "texture": "human-male-armor-coat-leather",
    "src": "./assets/atlas/male/armor/armor-coat-leather.png",
    "atlas": "./assets/atlas/80x80.json",
    "previewRect": [0, 160, 80, 80]
  },
  {
    "texture": "human-male-armor-coat",
    "src": "./assets/atlas/male/armor/armor-coat.png",
    "atlas": "./assets/atlas/80x80.json",
    "previewRect": [0, 160, 80, 80]
  },
  {
    "texture": "human-female-armor-robe-wizard",
    "src": "./assets/atlas/armor/armor-robe-wizard.png",
    "atlas": "./assets/atlas/80x80.json",
    "previewRect": [0, 160, 80, 80]
  },
  {
    "texture": "human-male-armor-robe-wizard",
    "src": "./assets/atlas/armor/armor-robe-wizard.png",
    "atlas": "./assets/atlas/80x80.json",
    "previewRect": [0, 160, 80, 80]
  },
  {
    "texture": "human-male-armor-robe-wizard-white",
    "src": "./assets/atlas/armor/armor-robe-wizard-white.png",
    "atlas": "./assets/atlas/80x80.json",
    "previewRect": [0, 160, 80, 80]
  },
  {
    "texture": "human-female-armor-robe-wizard-white",
    "src": "./assets/atlas/armor/armor-robe-wizard-white.png",
    "atlas": "./assets/atlas/80x80.json",
    "previewRect": [0, 160, 80, 80]
  },
  {
    "texture": "human-male-armor-robe-wizard",
    "src": "./assets/atlas/armor/armor-robe-wizard.png",
    "atlas": "./assets/atlas/80x80.json",
    "previewRect": [0, 160, 80, 80]
  },
  {
    "texture": "human-helmet-chef",
    "src": "./assets/atlas/helmet/helmet-chef.png",
    "atlas": "./assets/atlas/80x80.json",
    "previewRect": [0, 140, 80, 80]
  },
  {
    "texture": "human-helmet-wolf",
    "src": "./assets/atlas/helmet/helmet-wolf.png",
    "atlas": "./assets/atlas/80x80.json",
    "previewRect": [0, 140, 80, 80]
  },
  {
    "texture": "human-helmet-bunny",
    "src": "./assets/atlas/helmet/helmet-bunny.png",
    "atlas": "./assets/atlas/80x80.json",
    "previewRect": [0, 140, 80, 80]
  },
  {
    "texture": "human-helmet-crab",
    "src": "./assets/atlas/helmet/helmet-crab.png",
    "atlas": "./assets/atlas/80x80.json",
    "previewRect": [0, 140, 80, 80]
  },
  {
    "texture": "human-helmet-cap",
    "src": "./assets/atlas/helmet/helmet-cap.png",
    "atlas": "./assets/atlas/80x80.json",
    "previewRect": [0, 0, 80, 40]
  },
  {
    "texture": "human-helmet-cap-raccoon",
    "src": "./assets/atlas/helmet/helmet-cap-raccoon.png",
    "atlas": "./assets/atlas/80x80.json",
    "previewRect": [0, 80, 80, 40]
  },
  {
    "texture": "human-helmet-hood",
    "src": "./assets/atlas/helmet/helmet-hood.png",
    "atlas": "./assets/atlas/80x80.json",
    "previewRect": [0, 80, 80, 80]
  },
  {
    "texture": "human-helmet-armet",
    "src": "./assets/atlas/helmet/helmet-armet.png",
    "atlas": "./assets/atlas/80x80.json",
    "previewRect": [0, 80, 80, 80]
  },
  {
    "texture": "human-helmet-horned",
    "src": "./assets/atlas/helmet/helmet-horned.png",
    "atlas": "./assets/atlas/80x80.json",
    "previewRect": [0, 80, 80, 80]
  },
  {
    "texture": "human-accessory-glasses",
    "src": "./assets/atlas/accessory/accessory-glasses.png",
    "atlas": "./assets/atlas/80x80.json",
    "previewRect": [0, 140, 80, 80]
  },
  {
    "texture": "human-accessory-fins",
    "src": "./assets/atlas/accessory/accessory-fins.png",
    "atlas": "./assets/atlas/80x80.json",
    "previewRect": [0, 80, 80, 80]
  },
  {
    "texture": "human-gloves-cloth",
    "src": "./assets/atlas/gloves/gloves-cloth.png",
    "atlas": "./assets/atlas/80x80.json",
    "previewRect": [9, 331, 22, 18]
  },
  {
    "texture": "human-gloves-bracers",
    "src": "./assets/atlas/gloves/gloves-cloth.png",
    "atlas": "./assets/atlas/80x80.json",
    "previewRect": [131, 330, 17, 21]
  },
  {
    "texture": "human-gloves-fur",
    "src": "./assets/atlas/gloves/gloves-cloth.png",
    "atlas": "./assets/atlas/80x80.json",
    "previewRect": [50, 329, 20, 22]
  },
  {
    "texture": "human-gloves-plate",
    "src": "./assets/atlas/gloves/gloves-cloth.png",
    "atlas": "./assets/atlas/80x80.json",
    "previewRect": [91, 329, 19, 22]
  },
  {
    "texture": "human-boots-cloth",
    "src": "./assets/atlas/boots/boots-cloth.png",
    "atlas": "./assets/atlas/80x80.json",
    "previewRect": [9, 330, 22, 20]
  },
  {
    "texture": "human-boots-wings",
    "src": "./assets/atlas/boots/boots-cloth.png",
    "atlas": "./assets/atlas/80x80.json",
    "previewRect": [49, 328, 21, 23]
  },
  {
    "texture": "human-boots-plate",
    "src": "./assets/atlas/boots/boots-cloth.png",
    "atlas": "./assets/atlas/80x80.json",
    "previewRect": [88, 329, 23, 22]
  },
  {
    "texture": "human-pants-cloth",
    "src": "./assets/atlas/pants/pants-cloth.png",
    "atlas": "./assets/atlas/80x80.json",
    "previewRect": [0, 163, 80, 80]
  },
  {
    "texture": "weapon-dagger",
    "src": "./assets/atlas/hands/weapon-dagger.png",
    "atlas": "./assets/atlas/weapon.json",
    "previewRect": [39, 38, 15, 16]
  },
  {
    "texture": "weapon-cinquedea",
    "src": "./assets/atlas/hands/weapon-cinquedea.png",
    "atlas": "./assets/atlas/weapon.json",
    "previewRect": [38, 38, 16, 16]
  },
  {
    "texture": "weapon-dagger-carnage",
    "src": "./assets/atlas/hands/weapon-dagger-carnage.png",
    "atlas": "./assets/atlas/weapon.json",
    "previewRect": [34, 35, 20, 20]
  },
  {
    "texture": "weapon-dirk",
    "src": "./assets/atlas/hands/weapon-dirk.png",
    "atlas": "./assets/atlas/weapon.json",
    "previewRect": [37, 37, 17, 17]
  },
  {
    "texture": "weapon-hatchet",
    "src": "./assets/atlas/hands/weapon-hatchet.png",
    "atlas": "./assets/atlas/weapon.json",
    "previewRect": [35, 36, 18, 17]
  },
  {
    "texture": "weapon-tomahawk",
    "src": "./assets/atlas/hands/weapon-tomahawk.png",
    "atlas": "./assets/atlas/weapon.json",
    "previewRect": [30, 33, 22, 19]
  },
  {
    "texture": "weapon-wand-stick",
    "src": "./assets/atlas/hands/weapon-wand-stick.png",
    "atlas": "./assets/atlas/weapon.json",
    "previewRect": [31, 30, 23, 24]
  },
  {
    "texture": "weapon-wand-ball",
    "src": "./assets/atlas/hands/weapon-wand-ball.png",
    "atlas": "./assets/atlas/weapon.json",
    "previewRect": [31, 30, 23, 24]
  },
  {
    "texture": "weapon-wand-clover",
    "src": "./assets/atlas/hands/weapon-wand-clover.png",
    "atlas": "./assets/atlas/weapon.json",
    "previewRect": [35, 35, 19, 19]
  },
  {
    "texture": "weapon-staff-oak",
    "src": "./assets/atlas/hands/weapon-staff-oak.png",
    "atlas": "./assets/atlas/weapon.json",
    "previewRect": [30, 30, 24, 23]
  },
  {
    "texture": "weapon-staff-metal",
    "src": "./assets/atlas/hands/weapon-staff-metal.png",
    "atlas": "./assets/atlas/weapon.json",
    "previewRect": [30, 30, 24, 23]
  },
  {
    "texture": "weapon-staff-decanter",
    "src": "./assets/atlas/hands/weapon-staff-decanter.png",
    "atlas": "./assets/atlas/weapon.json",
    "previewRect": [31, 30, 24, 24]
  },
  {
    "texture": "weapon-staff-crystal",
    "src": "./assets/atlas/hands/weapon-staff-crystal.png",
    "atlas": "./assets/atlas/weapon.json",
    "previewRect": [32, 31, 23, 23]
  },
  {
    "texture": "weapon-sword-short",
    "src": "./assets/atlas/hands/weapon-sword-short.png",
    "atlas": "./assets/atlas/weapon.json",
    "previewRect": [35, 35, 19, 19]
  },
  {
    "texture": "weapon-sword-tizona",
    "src": "./assets/atlas/hands/weapon-sword-tizona.png",
    "atlas": "./assets/atlas/weapon.json",
    "previewRect": [31, 30, 23, 23]
  },
  {
    "texture": "weapon-sword-colada",
    "src": "./assets/atlas/hands/weapon-sword-colada.png",
    "atlas": "./assets/atlas/weapon.json",
    "previewRect": [30, 29, 24, 24]
  },
  {
    "texture": "weapon-spear",
    "src": "./assets/atlas/hands/weapon-spear.png",
    "atlas": "./assets/atlas/weapon.json",
    "previewRect": [24, 0, 32, 60]
  },
  {
    "texture": "weapon-halberd",
    "src": "./assets/atlas/hands/weapon-halberd.png",
    "atlas": "./assets/atlas/weapon.json",
    "previewRect": [10, 11, 46, 45]
  },
  {
    "texture": "weapon-spetum",
    "src": "./assets/atlas/hands/weapon-spetum.png",
    "atlas": "./assets/atlas/weapon.json",
    "previewRect": [9, 9, 47, 47]
  },
  {
    "texture": "weapon-cleaver",
    "src": "./assets/atlas/hands/weapon-cleaver.png",
    "atlas": "./assets/atlas/weapon.json",
    "previewRect": [30, 33, 28, 24]
  },
  {
    "texture": "weapon-club",
    "src": "./assets/atlas/hands/weapon-club.png",
    "atlas": "./assets/atlas/weapon.json",
    "previewRect": [35, 33, 19, 21]
  },
  {
    "texture": "weapon-hammer",
    "src": "./assets/atlas/hands/weapon-hammer.png",
    "atlas": "./assets/atlas/weapon.json",
    "previewRect": [32, 36, 25, 21]
  },
  {
    "texture": "weapon-cudgel",
    "src": "./assets/atlas/hands/weapon-cudgel.png",
    "atlas": "./assets/atlas/weapon.json",
    "previewRect": [36, 36, 21, 21]
  },
  {
    "texture": "weapon-scythe",
    "src": "./assets/atlas/hands/weapon-scythe.png",
    "atlas": "./assets/atlas/weapon.json",
    "previewRect": [28, 33, 24, 19]
  },
  {
    "texture": "weapon-sickle",
    "src": "./assets/atlas/hands/weapon-sickle.png",
    "atlas": "./assets/atlas/weapon.json",
    "previewRect": [28, 33, 24, 19]
  },
  {
    "texture": "weapon-harvester",
    "src": "./assets/atlas/hands/weapon-harvester.png",
    "atlas": "./assets/atlas/weapon.json",
    "previewRect": [28, 30, 24, 24]
  },
  {
    "texture": "weapon-wyrm-blade",
    "src": "./assets/atlas/hands/weapon-wyrm-blade.png",
    "atlas": "./assets/atlas/weapon.json",
    "previewRect": [25, 26, 31, 31]
  },
  {
    "texture": "weapon-claymore-soul",
    "src": "./assets/atlas/hands/weapon-claymore-soul.png",
    "atlas": "./assets/atlas/weapon.json",
    "previewRect": [15, 13, 42, 44]
  },
  {
    "texture": "weapon-katar",
    "src": "./assets/atlas/hands/weapon-katar.png",
    "atlas": "./assets/atlas/weapon.json",
    "previewRect": [36, 45, 19, 19]
  },
  {
    "texture": "weapon-spikes",
    "src": "./assets/atlas/hands/weapon-spikes.png",
    "atlas": "./assets/atlas/weapon.json",
    "previewRect": [35, 45, 19, 18]
  },
  {
    "texture": "weapon-claw",
    "src": "./assets/atlas/hands/weapon-claw.png",
    "atlas": "./assets/atlas/weapon.json",
    "previewRect": [35, 42, 23, 18]
  },
  {
    "texture": "weapon-gladius",
    "src": "./assets/atlas/hands/weapon-gladius.png",
    "atlas": "./assets/atlas/weapon.json",
    "previewRect": [30, 30, 26, 26]
  },
  {
    "texture": "weapon-claymore",
    "src": "./assets/atlas/hands/weapon-claymore.png",
    "atlas": "./assets/atlas/weapon.json",
    "previewRect": [29, 29, 28, 28]
  },
  {
    "texture": "weapon-scimitar",
    "src": "./assets/atlas/hands/weapon-scimitar.png",
    "atlas": "./assets/atlas/weapon.json",
    "previewRect": [29, 29, 27, 27]
  },
  {
    "texture": "weapon-talwar",
    "src": "./assets/atlas/hands/weapon-talwar.png",
    "atlas": "./assets/atlas/weapon.json",
    "previewRect": [29, 29, 27, 27]
  },
  {
    "texture": "weapon-shamshir",
    "src": "./assets/atlas/hands/weapon-shamshir.png",
    "atlas": "./assets/atlas/weapon.json",
    "previewRect": [33, 27, 20, 26]
  },
  {
    "texture": "weapon-scimitar-fox",
    "src": "./assets/atlas/hands/weapon-scimitar-fox.png",
    "atlas": "./assets/atlas/weapon.json",
    "previewRect": [29, 29, 27, 27]
  },
  {
    "texture": "shield-round",
    "src": "./assets/atlas/hands/shield-round.png",
    "atlas": "./assets/atlas/weapon.json",
    "previewRect": [40, 36, 20, 22]
  },
  {
    "texture": "shield-oval",
    "src": "./assets/atlas/hands/shield-oval.png",
    "atlas": "./assets/atlas/weapon.json",
    "previewRect": [41, 36, 18, 22]
  },
  {
    "texture": "shield-broken",
    "src": "./assets/atlas/hands/shield-broken.png",
    "atlas": "./assets/atlas/weapon.json",
    "previewRect": [44, 38, 17, 23]
  },
  {
    "texture": "shield-kite",
    "src": "./assets/atlas/hands/shield-kite.png",
    "atlas": "./assets/atlas/weapon.json",
    "previewRect": [43, 36, 17, 23]
  },
  {
    "texture": "shield-tower",
    "src": "./assets/atlas/hands/shield-tower.png",
    "atlas": "./assets/atlas/weapon.json",
    "previewRect": [44, 36, 16, 24]
  },
  {
    "texture": "shield-buckler",
    "src": "./assets/atlas/hands/shield-buckler.png",
    "atlas": "./assets/atlas/weapon.json",
    "previewRect": [41, 36, 20, 22]
  },
  {
    "texture": "shield-wyrm",
    "src": "./assets/atlas/hands/shield-wyrm.png",
    "atlas": "./assets/atlas/weapon.json",
    "previewRect": [38, 35, 24, 23]
  },
  {
    "texture": "shield-bone",
    "src": "./assets/atlas/hands/shield-bone.png",
    "atlas": "./assets/atlas/weapon.json",
    "previewRect": [41, 37, 19, 22]
  },
  {
    "texture": "shield-tower",
    "src": "./assets/atlas/hands/shield-tower.png",
    "atlas": "./assets/atlas/weapon.json",
    "previewRect": [42, 35, 16, 24]
  },
  {
    "texture": "ranged-shortBow",
    "src": "./assets/atlas/hands/ranged-shortBow.png",
    "atlas": "./assets/atlas/weapon.json",
    "previewRect": [43, 34, 24, 22]
  },
  {
    "texture": "ranged-longBow",
    "src": "./assets/atlas/hands/ranged-longBow.png",
    "atlas": "./assets/atlas/weapon.json",
    "previewRect": [41, 29, 30, 30]
  },
  {
    "texture": "ranged-shortBow-metal",
    "src": "./assets/atlas/hands/ranged-shortBow-metal.png",
    "atlas": "./assets/atlas/weapon.json",
    "previewRect": [45, 33, 22, 22]
  },
  {
    "texture": "ring-silver-plain",
    "src": "./assets/atlas/ring/ring-silver-plain.png",
    "atlas": "./assets/atlas/32x32-stackable.json",
    "previewRect": [0, 0, 32, 32]
  },
  {
    "texture": "ring-gold-plain",
    "src": "./assets/atlas/ring/ring-gold-plain.png",
    "atlas": "./assets/atlas/32x32-stackable.json",
    "previewRect": [0, 0, 32, 32]
  },
  {
    "texture": "ring-copper-plain",
    "src": "./assets/atlas/ring/ring-copper-plain.png",
    "atlas": "./assets/atlas/32x32-stackable.json",
    "previewRect": [0, 0, 32, 32]
  },
  {
    "texture": "ring-silver-sapphire",
    "src": "./assets/atlas/ring/ring-silver-sapphire.png",
    "atlas": "./assets/atlas/32x32-stackable.json",
    "previewRect": [0, 0, 32, 32]
  },
  {
    "texture": "ring-silver-ruby",
    "src": "./assets/atlas/ring/ring-silver-ruby.png",
    "atlas": "./assets/atlas/32x32-stackable.json",
    "previewRect": [0, 0, 32, 32]
  },
  {
    "texture": "amulet-silver-plain",
    "src": "./assets/atlas/amulet/amulet-silver-plain.png",
    "atlas": "./assets/atlas/32x32-stackable.json",
    "previewRect": [0, 0, 32, 32]
  },
  {
    "texture": "amulet-gold-plain",
    "src": "./assets/atlas/amulet/amulet-gold-plain.png",
    "atlas": "./assets/atlas/32x32-stackable.json",
    "previewRect": [0, 0, 32, 32]
  },
  {
    "texture": "amulet-gold-sapphire",
    "src": "./assets/atlas/amulet/amulet-gold-sapphire.png",
    "atlas": "./assets/atlas/32x32-stackable.json",
    "previewRect": [0, 0, 32, 32]
  },
  {
    "texture": "amulet-beads-red",
    "src": "./assets/atlas/amulet/amulet-beads-red.png",
    "atlas": "./assets/atlas/32x32-stackable.json",
    "previewRect": [0, 0, 32, 32]
  },
  {
    "texture": "amulet-beads-green",
    "src": "./assets/atlas/amulet/amulet-beads-green.png",
    "atlas": "./assets/atlas/32x32-stackable.json",
    "previewRect": [0, 0, 32, 32]
  },
  {
    "texture": "bag-small-pouch",
    "src": "./assets/atlas/bag/bag-small-pouch.png",
    "atlas": "./assets/atlas/32x32-stackable.json",
    "previewRect": [0, 0, 32, 32]
  },
  {
    "texture": "bag-large-pouch",
    "src": "./assets/atlas/bag/bag-large-pouch.png",
    "atlas": "./assets/atlas/32x32-stackable.json",
    "previewRect": [0, 0, 32, 32]
  },
  {
    "texture": "bag-basket",
    "src": "./assets/atlas/bag/bag-basket.png",
    "atlas": "./assets/atlas/32x32-stackable.json",
    "previewRect": [0, 0, 32, 32]
  },
  {
    "texture": "stackable-skull",
    "src": "./assets/atlas/stackable/stackable-skull.png",
    "atlas": "./assets/atlas/32x32-stackable.json",
    "previewRect": [0, 0, 32, 32]
  },
  {
    "texture": "stackable-pelt",
    "src": "./assets/atlas/stackable/stackable-pelt.png",
    "atlas": "./assets/atlas/32x32-stackable.json",
    "previewRect": [0, 0, 32, 32]
  },
  {
    "texture": "stackable-stone",
    "src": "./assets/atlas/stackable/stackable-stone.png",
    "atlas": "./assets/atlas/32x32-stackable.json",
    "previewRect": [0, 0, 32, 32]
  },
  {
    "texture": "stackable-scale-wyrm",
    "src": "./assets/atlas/stackable/stackable-scale-wyrm.png",
    "atlas": "./assets/atlas/32x32-stackable.json",
    "previewRect": [0, 0, 32, 32]
  },
  {
    "texture": "stackable-ore-gold",
    "src": "./assets/atlas/stackable/stackable-ore-gold.png",
    "atlas": "./assets/atlas/32x32-stackable.json",
    "previewRect": [0, 0, 32, 32]
  },
  {
    "texture": "stackable-leaves",
    "src": "./assets/atlas/stackable/stackable-leaves.png",
    "atlas": "./assets/atlas/32x32-stackable.json",
    "previewRect": [0, 0, 32, 32]
  },
  {
    "texture": "stackable-crystal",
    "src": "./assets/atlas/stackable/stackable-crystal.png",
    "atlas": "./assets/atlas/32x32-stackable.json",
    "previewRect": [0, 0, 32, 32]
  },
  {
    "texture": "stackable-shell",
    "src": "./assets/atlas/stackable/stackable-shell.png",
    "atlas": "./assets/atlas/32x32-stackable.json",
    "previewRect": [0, 0, 32, 32]
  },
  {
    "texture": "stackable-flower-orchid",
    "src": "./assets/atlas/stackable/stackable-flower-orchid.png",
    "atlas": "./assets/atlas/32x32-stackable.json",
    "previewRect": [0, 0, 32, 32]
  },
  {
    "texture": "stackable-flower-daisy",
    "src": "./assets/atlas/stackable/stackable-flower-daisy.png",
    "atlas": "./assets/atlas/32x32-stackable.json",
    "previewRect": [0, 0, 32, 32]
  },
  {
    "texture": "stackable-clover",
    "src": "./assets/atlas/stackable/stackable-clover.png",
    "atlas": "./assets/atlas/32x32-stackable.json",
    "previewRect": [0, 0, 32, 32]
  },
  {
    "texture": "stackable-root",
    "src": "./assets/atlas/stackable/stackable-root.png",
    "atlas": "./assets/atlas/32x32-stackable.json",
    "previewRect": [0, 0, 32, 32]
  },
  {
    "texture": "stackable-tooth",
    "src": "./assets/atlas/stackable/stackable-tooth.png",
    "atlas": "./assets/atlas/32x32-stackable.json",
    "previewRect": [0, 0, 32, 32]
  },
  {
    "texture": "stackable-claw",
    "src": "./assets/atlas/stackable/stackable-claw.png",
    "atlas": "./assets/atlas/32x32-stackable.json",
    "previewRect": [0, 0, 32, 32]
  },
  {
    "texture": "stackable-bsporangium",
    "src": "./assets/atlas/stackable/stackable-bsporangium.png",
    "atlas": "./assets/atlas/32x32-stackable.json",
    "previewRect": [0, 0, 32, 32]
  },
  {
    "texture": "stackable-apple",
    "src": "./assets/atlas/stackable/stackable-apple.png",
    "atlas": "./assets/atlas/32x32-stackable.json",
    "previewRect": [0, 0, 32, 32]
  },
  {
    "texture": "stackable-grapes",
    "src": "./assets/atlas/stackable/stackable-grapes.png",
    "atlas": "./assets/atlas/32x32-stackable.json",
    "previewRect": [0, 0, 32, 32]
  },
  {
    "texture": "stackable-carrot",
    "src": "./assets/atlas/stackable/stackable-carrot.png",
    "atlas": "./assets/atlas/32x32-stackable.json",
    "previewRect": [0, 0, 32, 32]
  },
  {
    "texture": "stackable-egg",
    "src": "./assets/atlas/stackable/stackable-egg.png",
    "atlas": "./assets/atlas/32x32-stackable.json",
    "previewRect": [0, 0, 32, 32]
  },
  {
    "texture": "stackable-mushroom",
    "src": "./assets/atlas/stackable/stackable-mushroom.png",
    "atlas": "./assets/atlas/32x32-stackable.json",
    "previewRect": [0, 0, 32, 32]
  },
  {
    "texture": "stackable-shitake",
    "src": "./assets/atlas/stackable/stackable-shitake.png",
    "atlas": "./assets/atlas/32x32-stackable.json",
    "previewRect": [0, 0, 32, 32]
  },
  {
    "texture": "stackable-orange",
    "src": "./assets/atlas/stackable/stackable-orange.png",
    "atlas": "./assets/atlas/32x32-stackable.json",
    "previewRect": [0, 0, 32, 32]
  },
  {
    "texture": "stackable-meat",
    "src": "./assets/atlas/stackable/stackable-meat.png",
    "atlas": "./assets/atlas/32x32-stackable.json",
    "previewRect": [0, 0, 32, 32]
  },
  {
    "texture": "stackable-cheese",
    "src": "./assets/atlas/stackable/stackable-cheese.png",
    "atlas": "./assets/atlas/32x32-stackable.json",
    "previewRect": [0, 0, 32, 32]
  },
  {
    "texture": "stackable-potion-small-hp",
    "src": "./assets/atlas/stackable/stackable-potion-small-hp.png",
    "atlas": "./assets/atlas/32x32-stackable.json",
    "previewRect": [0, 0, 32, 32]
  },
  {
    "texture": "stackable-potion-medium-hp",
    "src": "./assets/atlas/stackable/stackable-potion-medium-hp.png",
    "atlas": "./assets/atlas/32x32-stackable.json",
    "previewRect": [0, 0, 32, 32]
  },
  {
    "texture": "stackable-potion-small-mp",
    "src": "./assets/atlas/stackable/stackable-potion-small-mp.png",
    "atlas": "./assets/atlas/32x32-stackable.json",
    "previewRect": [0, 0, 32, 32]
  },
  {
    "texture": "stackable-potion-medium-mp",
    "src": "./assets/atlas/stackable/stackable-potion-medium-mp.png",
    "atlas": "./assets/atlas/32x32-stackable.json",
    "previewRect": [0, 0, 32, 32]
  },
  {
    "texture": "scroll-gray",
    "src": "./assets/atlas/spell/scroll-gray.png",
    "atlas": "./assets/atlas/32x32-stackable.json",
    "previewRect": [0, 0, 32, 32]
  },
  {
    "texture": "scroll-red",
    "src": "./assets/atlas/spell/scroll-red.png",
    "atlas": "./assets/atlas/32x32-stackable.json",
    "previewRect": [0, 0, 32, 32]
  },
  {
    "texture": "scroll-green",
    "src": "./assets/atlas/spell/scroll-green.png",
    "atlas": "./assets/atlas/32x32-stackable.json",
    "previewRect": [0, 0, 32, 32]
  },
  {
    "texture": "scroll-blue",
    "src": "./assets/atlas/spell/scroll-blue.png",
    "atlas": "./assets/atlas/32x32-stackable.json",
    "previewRect": [0, 0, 32, 32]
  },
  {
    "texture": "scroll-yellow",
    "src": "./assets/atlas/spell/scroll-yellow.png",
    "atlas": "./assets/atlas/32x32-stackable.json",
    "previewRect": [0, 0, 32, 32]
  },
  {
    "texture": "spell-poison",
    "src": "./assets/atlas/spell/spell-poison.png",
    "atlas": "./assets/atlas/32x32-stackable.json",
    "previewRect": [0, 0, 32, 32]
  },
  {
    "texture": "spell-fortune",
    "src": "./assets/atlas/spell/spell-fortune.png",
    "atlas": "./assets/atlas/32x32-stackable.json",
    "previewRect": [0, 0, 32, 32]
  },
  {
    "texture": "spell-slow",
    "src": "./assets/atlas/spell/spell-slow.png",
    "atlas": "./assets/atlas/32x32-stackable.json",
    "previewRect": [0, 0, 32, 32]
  },
  {
    "texture": "spell-stun",
    "src": "./assets/atlas/spell/spell-stun.png",
    "atlas": "./assets/atlas/32x32-stackable.json",
    "previewRect": [0, 0, 32, 32]
  },
  {
    "texture": "spell-evasion",
    "src": "./assets/atlas/spell/spell-evasion.png",
    "atlas": "./assets/atlas/32x32-stackable.json",
    "previewRect": [0, 0, 32, 32]
  },
  {
    "texture": "spell-haste",
    "src": "./assets/atlas/spell/spell-haste.png",
    "atlas": "./assets/atlas/32x32-stackable.json",
    "previewRect": [0, 0, 32, 32]
  },
  {
    "texture": "spell-brute",
    "src": "./assets/atlas/spell/spell-brute.png",
    "atlas": "./assets/atlas/32x32-stackable.json",
    "previewRect": [0, 0, 32, 32]
  },
  {
    "texture": "spell-genius",
    "src": "./assets/atlas/spell/spell-genius.png",
    "atlas": "./assets/atlas/32x32-stackable.json",
    "previewRect": [0, 0, 32, 32]
  },
  {
    "texture": "spell-endurance",
    "src": "./assets/atlas/spell/spell-endurance.png",
    "atlas": "./assets/atlas/32x32-stackable.json",
    "previewRect": [0, 0, 32, 32]
  },
  {
    "texture": "spell-regeneration",
    "src": "./assets/atlas/spell/spell-regeneration.png",
    "atlas": "./assets/atlas/32x32-stackable.json",
    "previewRect": [0, 0, 32, 32]
  },
  {
    "texture": "spell-fireball",
    "src": "./assets/atlas/spell/spell-fireball.png",
    "atlas": "./assets/atlas/32x32-stackable.json",
    "previewRect": [0, 0, 32, 32]
  },
  {
    "texture": "spell-adrenaline",
    "src": "./assets/atlas/spell/spell-adrenaline.png",
    "atlas": "./assets/atlas/32x32-stackable.json",
    "previewRect": [0, 0, 32, 32]
  },
  {
    "texture": "spell-stimulant",
    "src": "./assets/atlas/spell/spell-stimulant.png",
    "atlas": "./assets/atlas/32x32-stackable.json",
    "previewRect": [0, 0, 32, 32]
  },
  {
    "texture": "spell-siphon",
    "src": "./assets/atlas/spell/spell-siphon.png",
    "atlas": "./assets/atlas/32x32-stackable.json",
    "previewRect": [0, 0, 32, 32]
  },
  {
    "texture": "spell-vampire",
    "src": "./assets/atlas/spell/spell-vampire.png",
    "atlas": "./assets/atlas/32x32-stackable.json",
    "previewRect": [0, 0, 32, 32]
  },
  {
    "texture": "spell-quake",
    "src": "./assets/atlas/spell/spell-quake.png",
    "atlas": "./assets/atlas/32x32-stackable.json",
    "previewRect": [0, 0, 32, 32]
  },
  {
    "texture": "icons",
    "src": "./assets/images/icons.png",
    "atlas": "./assets/atlas/32x32-icons.json",
    "previewRect": [0, 0, 32, 32]
  }
]
